SpaceCherenkovSimulator/Cherenkov_run_tuple.py
SpaceCherenkovSimulator/SpaceCherenkovSimulator.py
SpaceCherenkovSimulator/__init__.py
SpaceCherenkovSimulator/default_settings_variables.py
SpaceCherenkovSimulator/full_background_running_tools.py
SpaceCherenkovSimulator/multispectra_running_tools.py
SpaceCherenkovSimulator/spectra_running_tools.py
SpaceCherenkovSimulator/tools_for_Cherenkov_runs.py
SpaceCherenkovSimulator/Analysis_macros/Analysis.g4mac
SpaceCherenkovSimulator/Analysis_macros/Analysis_2_radiators.g4mac
SpaceCherenkovSimulator/Analysis_macros/Analysis_fluence_m.g4mac
SpaceCherenkovSimulator/Analysis_macros/Analysis_reaction_m.g4mac
SpaceCherenkovSimulator/IRENE8_input_data/IRENE8_450_circ_orbit_coords.txt
SpaceCherenkovSimulator/IRENE8_input_data/IRENE8_450_circ_orbit_electrons.txt
SpaceCherenkovSimulator/IRENE8_input_data/IRENE8_450_circ_orbit_protons.txt
SpaceCherenkovSimulator/gdml_templates/template_gdml_file_to_use_1_radiators.gdml
SpaceCherenkovSimulator/gdml_templates/template_gdml_file_to_use_2_radiators.gdml
SpaceCherenkovSimulator/input_macro_templates/template_gras_input_macro.in
SpaceCherenkovSimulator/interplanetary_spectra/GLE05spectrum_multipliedby1.csv
SpaceCherenkovSimulator/interplanetary_spectra/GLE21spectrum_multipliedby1.csv
SpaceCherenkovSimulator/interplanetary_spectra/cosmic_ray_spectrum_file_for_GRAS.csv
SpaceCherenkovSimulator/photon_detection_efficiencies/BC_PDE.csv
SpaceCherenkovSimulator/photon_detection_efficiencies/SiPM_PDE.csv
SpaceCherenkovSimulator-0.2.9.dist-info/LICENSE
SpaceCherenkovSimulator-0.2.9.dist-info/METADATA
SpaceCherenkovSimulator-0.2.9.dist-info/WHEEL
SpaceCherenkovSimulator-0.2.9.dist-info/top_level.txt
SpaceCherenkovSimulator-0.2.9.dist-info/RECORD
