Metadata-Version: 2.1
Name: SpaceCherenkovSimulator
Version: 0.2.9
Summary: Python library containing tools for simulating Cherenkov detector count rates in space.
Home-page: https://github.com/ssc-maire/SpaceCherenkovSimulator
Author: Space Environment and Protection Group, University of Surrey
License: CC BY-NC-SA 4.0
Keywords: space physics earth asymptotic trajectory Cherenkov detector Geant4 GRAS geomagnetic rigidity magnetocosmics trapped particles AE8 AP8
License-File: LICENSE
Requires-Dist: AsympDirsCalculator>=1.0.8
Requires-Dist: CosRayModifiedISO>=1.2.3
Requires-Dist: geopandas>=0.11.1
Requires-Dist: joblib>=1.2.0
Requires-Dist: matplotlib>=3.5.2
Requires-Dist: numpy>=1.23.1
Requires-Dist: pandas>=1.4.3
Requires-Dist: ParticleRigidityCalculationTools>=1.5.4
Requires-Dist: pyarrow>=12.0.0
Requires-Dist: scipy>=1.10.1
Requires-Dist: seaborn>=0.13.0
Requires-Dist: setuptools>=45.2.0
Requires-Dist: sketch>=0.4.2
Requires-Dist: spacepy>=0.4.1
Requires-Dist: tqdm>=4.30.0
Requires-Dist: uncertainties>=3.1.7
Requires-Dist: uproot>=5.1.2
